{"data":{"devices":[{"id":"1A:67:F3:96:2E:A2:43:DF","name":"Curtain","model":"H70B1","vendor":"govee","isOn":false,"brightness":0,"color":{"r":255,"g":255,"b":255},"capabilities":{"modes":true,"scenes":true,"music":true},"originalData":{"device":"1A:67:F3:96:2E:A2:43:DF","model":"H70B1","deviceName":"Curtain","controllable":true,"properties":{"colorTem":{"range":{"min":2000,"max":9000}}},"retrievable":true,"supportCmds":["turn","brightness","color","colorTem"]}},{"id":"21:5D:DD:42:05:C6:31:6F","name":"Harvard Diploma","model":"H6167","vendor":"govee","isOn":false,"brightness":0,"color":{"r":255,"g":255,"b":255},"capabilities":{"modes":true,"scenes":true,"music":true},"originalData":{"device":"21:5D:DD:42:05:C6:31:6F","model":"H6167","deviceName":"Harvard Diploma","controllable":true,"properties":{"colorTem":{"range":{"min":2000,"max":9000}}},"retrievable":true,"supportCmds":["turn","brightness","color","colorTem"]}},{"id":"24:13:DD:42:05:C6:32:68","name":"Office TV Backlight","model":"H6167","vendor":"govee","isOn":false,"brightness":0,"color":{"r":255,"g":255,"b":255},"capabilities":{"modes":true,"scenes":true,"music":true},"originalData":{"device":"24:13:DD:42:05:C6:32:68","model":"H6167","deviceName":"Office TV Backlight","controllable":true,"properties":{"colorTem":{"range":{"min":2000,"max":9000}}},"retrievable":true,"supportCmds":["turn","brightness","color","colorTem"]}},{"id":"eb8f2f49f55123b3b4bqua","name":"Prism","model":"Smart Light","vendor":"tuya","isOn":false,"brightness":100,"color":{"r":255,"g":255,"b":255},"capabilities":{"modes":true,"scenes":true,"music":false},"originalData":{"active_time":1763743981,"category":"dd","category_name":"Strip Lights","create_time":1689901080,"gateway_id":"","icon":"smart/icon/ay1531122507771gALCb/cc9b34189b6b3b99545e0062c369ef5b.png","id":"eb8f2f49f55123b3b4bqua","ip":"167.224.143.173","lat":"36.1","local_key":"z:IleEp+JUOcA1b9","lon":"-94.12","model":"T103 IR19","name":"Prism","online":true,"owner_id":"162729826","product_id":"xwbfgdehsrlje4af","product_name":"Smart Light","sub":false,"time_zone":"-06:00","update_time":1763760822,"uuid":"06c26f5e0c77e3c1"}}]},"debug":{"govee":{"keyPresent":true,"count":3,"error":null},"tuya":{"keyPresent":true,"count":1,"rawCount":1}}}